batch_executor/__init__.py
batch_executor/config.py
batch_executor/constants.py
batch_executor/custom_logger.py
batch_executor/main.py
batch_executor/utils.py
batch_executor/validator.py
batch_executor/writer.py
batch_executor-0.3.0.dist-info/licenses/LICENSE
batch_executor-0.3.0.dist-info/METADATA
batch_executor-0.3.0.dist-info/WHEEL
batch_executor-0.3.0.dist-info/top_level.txt
batch_executor-0.3.0.dist-info/RECORD
