Metadata-Version: 2.4
Name: batch_executor
Version: 0.3.0
Summary: A high-performance batch executor supporting async, threading, multiprocessing, and hybrid execution modes with progress bars and logging.
Author-email: Rex Wang <1073853456@qq.com>
Maintainer-email: Rex Wang <1073853456@qq.com>
License: MIT license
License-File: LICENSE
Requires-Dist: click
Requires-Dist: tqdm
Requires-Dist: func_timeout
Requires-Dist: psutil
Requires-Dist: colorama
Requires-Dist: httpx
Provides-Extra: dev
Requires-Dist: coverage; extra == "dev"
Requires-Dist: pytest; extra == "dev"
Requires-Dist: pytest-asyncio; extra == "dev"
Requires-Dist: asyncio; extra == "dev"
Requires-Dist: pytest-cov; extra == "dev"
Requires-Dist: pytest-mock; extra == "dev"
Requires-Dist: pytest-xdist; extra == "dev"
Requires-Dist: pytest-pythonpath; extra == "dev"
Provides-Extra: docs
Requires-Dist: mkdocs>=1.4.0; extra == "docs"
Requires-Dist: mkdocs-material>=9.0.0; extra == "docs"
Requires-Dist: mkdocs-static-i18n>=0.5.0; extra == "docs"
Requires-Dist: pymdown-extensions; extra == "docs"
Dynamic: license-file
